CHANGELOG.md
MANIFEST.in
README.md
setup.py
scp/app/sdk/__init__.py
scp/app/sdk/appignore.py
scp/app/sdk/build.py
scp/app/sdk/configuration.py
scp/app/sdk/create.py
scp/app/sdk/csfe.py
scp/app/sdk/manifest.py
scp/app/sdk/runner.py
scp/app/sdk/service.py
scp/app/sdk/ui_plugins.py
scp/app/sdk/validate.py
scp/app/sdk/version.py
scp/app/sdk/voicebot.py
scp/app/sdk/cli/__init__.py
scp/app/sdk/cli/__main__.py
scp/app/sdk/cli/config.py
scp/app/sdk/cli/documentation.py
scp/app/sdk/cli/scp_config.py
scp/app/sdk/cli/server.py
scp/app/sdk/cli/utils.py
scp/app/sdk/cli/version_check.py
scp/app/sdk/cli/cmd/build.py
scp/app/sdk/cli/cmd/configure.py
scp/app/sdk/cli/cmd/create.py
scp/app/sdk/cli/cmd/publish.py
scp/app/sdk/cli/cmd/run.py
scp/app/sdk/cli/cmd/validate.py
scp/app/sdk/schema/__init__.py
scp/app/sdk/schema/manifest.py
scp/app/sdk/schema/ui_plugin.py
scp/app/sdk/scripts/__init__.py
scp/app/sdk/scripts/migrate.py
scp/app/sdk/scripts/user.py
scp/app/sdk/studio/__init__.py
scp/app/sdk/studio/py.typed
scp/app/sdk/studio/studio.py
scp/app/sdk/template/__init__.py
scp/app/sdk/template/template/.appignore
scp/app/sdk/template/template/README.md
scp/app/sdk/template/template/manifest.yaml.j2
scp/app/sdk/template/template/assets/icon.png
scp/app/sdk/template/template/install/example_schema.json
scp/app/sdk/template/template/install/install
scp/app/sdk/template/template/install/migrate
scp/app/sdk/template/template/install/schema.json
scp/app/sdk/template/template/install/ui_plugin.json
scp/app/sdk/template/template/install/uninstall
scp_app_sdk.egg-info/PKG-INFO
scp_app_sdk.egg-info/SOURCES.txt
scp_app_sdk.egg-info/dependency_links.txt
scp_app_sdk.egg-info/entry_points.txt
scp_app_sdk.egg-info/requires.txt
scp_app_sdk.egg-info/top_level.txt