Metadata-Version: 2.4
Name: scp-app-sdk
Version: 1.6.0
Summary: SCP APP SDK
Author: Dstny
Requires-Python: >=3.7
Requires-Dist: marshmallow==3.*
Requires-Dist: marshmallow-oneofschema==3.*
Requires-Dist: click==8.*
Requires-Dist: jinja2==3.*
Requires-Dist: requests==2.*
Requires-Dist: PyYAML==6.*
Requires-Dist: kubernetes==34.*
Requires-Dist: pathspec==0.12.1
Provides-Extra: test
Requires-Dist: mypy==1.18.2; extra == "test"
Requires-Dist: mypy-baseline==0.7.3; extra == "test"
Requires-Dist: pytest; extra == "test"
Requires-Dist: pytest-cov; extra == "test"
Requires-Dist: types-PyYAML; extra == "test"
Requires-Dist: types-requests; extra == "test"
Requires-Dist: kubernetes-typed; extra == "test"
Requires-Dist: types-setuptools; extra == "test"
Dynamic: author
Dynamic: description
Dynamic: description-content-type
Dynamic: provides-extra
Dynamic: requires-dist
Dynamic: requires-python
Dynamic: summary
